batchmp/__init__.py
batchmp/cli/__init__.py
batchmp/cli/base/__init__.py
batchmp/cli/base/bmp_dispatch.py
batchmp/cli/base/bmp_options.py
batchmp/cli/base/vchk.py
batchmp/cli/bmfp/__init__.py
batchmp/cli/bmfp/bmfp_dispatch.py
batchmp/cli/bmfp/bmfp_options.py
batchmp/cli/renamer/__init__.py
batchmp/cli/renamer/renamer_dispatch.py
batchmp/cli/renamer/renamer_options.py
batchmp/cli/tagger/__init__.py
batchmp/cli/tagger/tagger_dispatch.py
batchmp/cli/tagger/tagger_options.py
batchmp/commons/__init__.py
batchmp/commons/chainedhandler.py
batchmp/commons/descriptors.py
batchmp/commons/progressbar.py
batchmp/commons/taskprocessor.py
batchmp/commons/utils.py
batchmp/ffmptools/__init__.py
batchmp/ffmptools/ffrunner.py
batchmp/ffmptools/ffutils.py
batchmp/ffmptools/ffcommands/__init__.py
batchmp/ffmptools/ffcommands/cmdopt.py
batchmp/ffmptools/ffcommands/convert.py
batchmp/ffmptools/ffcommands/cuesplit.py
batchmp/ffmptools/ffcommands/denoise.py
batchmp/ffmptools/ffcommands/fragment.py
batchmp/ffmptools/ffcommands/normalize_peak.py
batchmp/ffmptools/ffcommands/segment.py
batchmp/ffmptools/ffcommands/silencesplit.py
batchmp/ffmptools/processors/__init__.py
batchmp/ffmptools/processors/basefp.py
batchmp/ffmptools/processors/ffentry.py
batchmp/ffmptools/utils/__init__.py
batchmp/ffmptools/utils/cueparse.py
batchmp/ffmptools/utils/cuesheet.py
batchmp/fstools/__init__.py
batchmp/fstools/dirtools.py
batchmp/fstools/fsutils.py
batchmp/fstools/rename.py
batchmp/fstools/walker.py
batchmp/fstools/builders/__init__.py
batchmp/fstools/builders/fsb.py
batchmp/fstools/builders/fsentry.py
batchmp/fstools/builders/fsprms.py
batchmp/tags/__init__.py
batchmp/tags/handlers/__init__.py
batchmp/tags/handlers/basehandler.py
batchmp/tags/handlers/ffmphandler.py
batchmp/tags/handlers/mtghandler.py
batchmp/tags/handlers/pmhandler.py
batchmp/tags/handlers/tagsholder.py
batchmp/tags/handlers/ffmphandlers/__init__.py
batchmp/tags/handlers/ffmphandlers/base.py
batchmp/tags/output/__init__.py
batchmp-1.4.dist-info/licenses/LICENSE
batchmp-1.4.dist-info/METADATA
batchmp-1.4.dist-info/WHEEL
batchmp-1.4.dist-info/entry_points.txt
batchmp-1.4.dist-info/top_level.txt
batchmp-1.4.dist-info/zip-safe
batchmp-1.4.dist-info/RECORD
