Metadata-Version: 2.4
Name: batchmp
Version: 1.4
Summary: Command-line tools for batch media processing
Home-page: https://github.com/akpw/batch-mp-tools
Author: Arseniy Kuznetsov
Author-email: k.arseniy@gmail.com
License: GPL-2.0-or-later
Keywords: batch processing media video audio CLI rename tags ID3
Classifier: Development Status :: 4 - Beta
Classifier: Programming Language :: Python
Classifier: Programming Language :: Python :: 3.6
Classifier: Programming Language :: Python :: 3 :: Only
Classifier: Intended Audience :: End Users/Desktop
Classifier: Intended Audience :: Developers
Classifier: Intended Audience :: System Administrators
Classifier: Intended Audience :: Information Technology
Classifier: Operating System :: OS Independent
Classifier: Topic :: Multimedia :: Sound/Audio
Classifier: Topic :: Multimedia :: Sound/Audio :: Analysis
Classifier: Topic :: Multimedia :: Sound/Audio :: Conversion
Classifier: Topic :: Multimedia :: Video
Classifier: Topic :: Multimedia :: Video :: Conversion
Classifier: Topic :: Software Development :: Libraries
Classifier: Topic :: Utilities
License-File: LICENSE
Requires-Dist: mutagen>=1.27
Requires-Dist: pygtrie>=2.3.2
Requires-Dist: filetype>=1.0.7
Requires-Dist: mediafile>=0.13.0
Dynamic: author
Dynamic: author-email
Dynamic: classifier
Dynamic: description
Dynamic: description-content-type
Dynamic: home-page
Dynamic: keywords
Dynamic: license
Dynamic: license-file
Dynamic: requires-dist
Dynamic: summary
